{"success": true, "results": [{"date": "2021-05-30", "name": "Alabama", "id": "USA_US-AL", "total_count": 1, "lineage_count": 0, "cum_total_count": 223, "cum_lineage_count": 0, "proportion": 0.0, "proportion_ci_lower": 2.199479106829827e-06, "proportion_ci_upper": 0.011188622445017147}, {"date": "2021-06-04", "name": "Alaska", "id": "USA_US-AK", "total_count": 7, "lineage_count": 0, "cum_total_count": 941, "cum_lineage_count": 6, "proportion": 0.006376195536663124, "proportion_ci_lower": 0.002665646038557876, "proportion_ci_upper": 0.013095345331381236}, {"date": "2021-06-02", "name": "Arizona", "id": "USA_US-AZ", "total_count": 6, "lineage_count": 0, "cum_total_count": 1883, "cum_lineage_count": 11, "proportion": 0.005841741901221455, "proportion_ci_lower": 0.0031075509732139918, "proportion_ci_upper": 0.010087447223311341}, {"date": "2021-05-28", "name": "Arkansas", "id": "USA_US-AR", "total_count": 2, "lineage_count": 0, "cum_total_count": 275, "cum_lineage_count": 1, "proportion": 0.0036363636363636364, "proportion_ci_lower": 0.00039263525153582283, "proportion_ci_upper": 0.016868700059851305}, {"date": "2021-06-01", "name": "California", "id": "USA_US-CA", "total_count": 40, "lineage_count": 0, "cum_total_count": 6951, "cum_lineage_count": 38, "proportion": 0.00546683930369731, "proportion_ci_lower": 0.003932057797248689, "proportion_ci_upper": 0.007412859735885569}, {"date": "2021-05-17", "name": "California, Los Angeles County", "id": "USA_US-None", "total_count": 1, "lineage_count": 0, "cum_total_count": 3, "cum_lineage_count": 0, "proportion": 0.0, "proportion_ci_lower": 0.00015063602543656854, "proportion_ci_upper": 0.5355832430429506}, {"date": "2021-06-01", "name": "Colorado", "id": "USA_US-CO", "total_count": 8, "lineage_count": 0, "cum_total_count": 5507, "cum_lineage_count": 9, "proportion": 0.0016342836390049029, "proportion_ci_lower": 0.0008089514409619101, "proportion_ci_upper": 0.0029806326359960167}, {"date": "2021-05-29", "name": "Connecticut", "id": "USA_US-CT", "total_count": 3, "lineage_count": 0, "cum_total_count": 2079, "cum_lineage_count": 16, "proportion": 0.007696007696007696, "proportion_ci_lower": 0.0045873309986839, "proportion_ci_upper": 0.01217045306518516}, {"date": "2021-05-26", "name": "Delaware", "id": "USA_US-DE", "total_count": 1, "lineage_count": 0, "cum_total_count": 605, "cum_lineage_count": 0, "proportion": 0.0, "proportion_ci_lower": 8.112917265589552e-07, "proportion_ci_upper": 0.004141655715564158}, {"date": "2021-06-03", "name": "District of Columbia", "id": "USA_US-DC", "total_count": 1, "lineage_count": 0, "cum_total_count": 222, "cum_lineage_count": 1, "proportion": 0.0045045045045045045, "proportion_ci_lower": 0.00048645553401686665, "proportion_ci_upper": 0.02085816000444818}, {"date": "2021-05-31", "name": "Florida", "id": "USA_US-FL", "total_count": 9, "lineage_count": 0, "cum_total_count": 8589, "cum_lineage_count": 29, "proportion": 0.0033764116893701245, "proportion_ci_lower": 0.002310041903164864, "proportion_ci_upper": 0.004776886284654114}, {"date": "2021-06-09", "name": "Georgia", "id": "USA_US-GA", "total_count": 8, "lineage_count": 0, "cum_total_count": 1444, "cum_lineage_count": 26, "proportion": 0.018005540166204988, "proportion_ci_lower": 0.012075714847074545, "proportion_ci_upper": 0.025862103726345897}, {"date": "2021-05-11", "name": "Guam", "id": "USA_US-None", "total_count": 3, "lineage_count": 0, "cum_total_count": 18, "cum_lineage_count": 1, "proportion": 0.05555555555555555, "proportion_ci_lower": 0.006061344165326898, "proportion_ci_upper": 0.231611808489526}, {"date": "2021-05-28", "name": "Hawaii", "id": "USA_US-HI", "total_count": 1, "lineage_count": 0, "cum_total_count": 261, "cum_lineage_count": 3, "proportion": 0.011494252873563218, "proportion_ci_lower": 0.0032476180761250068, "proportion_ci_upper": 0.03035379440848862}, {"date": "2021-05-30", "name": "Idaho", "id": "USA_US-ID", "total_count": 1, "lineage_count": 0, "cum_total_count": 208, "cum_lineage_count": 0, "proportion": 0.0, "proportion_ci_lower": 2.35790456537473e-06, "proportion_ci_upper": 0.011989672608352698}, {"date": "2021-06-01", "name": "Illinois", "id": "USA_US-IL", "total_count": 1, "lineage_count": 0, "cum_total_count": 5949, "cum_lineage_count": 59, "proportion": 0.009917633215666499, "proportion_ci_lower": 0.0076315487029069845, "proportion_ci_upper": 0.012680089587643995}, {"date": "2021-06-04", "name": "Indiana", "id": "USA_US-IN", "total_count": 23, "lineage_count": 1, "cum_total_count": 2322, "cum_lineage_count": 13, "proportion": 0.005598621877691645, "proportion_ci_lower": 0.0031416407960501605, "proportion_ci_upper": 0.009282924403497872}, {"date": "2021-06-03", "name": "Iowa", "id": "USA_US-IA", "total_count": 1, "lineage_count": 0, "cum_total_count": 191, "cum_lineage_count": 0, "proportion": 0.0, "proportion_ci_lower": 2.5674954696035283e-06, "proportion_ci_upper": 0.013048434268555786}, {"date": "2021-06-07", "name": "Kansas", "id": "USA_US-KS", "total_count": 20, "lineage_count": 0, "cum_total_count": 1269, "cum_lineage_count": 4, "proportion": 0.0031520882584712374, "proportion_ci_lower": 0.0010648858237657845, "proportion_ci_upper": 0.00747744478928114}, {"date": "2021-05-29", "name": "Kentucky", "id": "USA_US-KY", "total_count": 1, "lineage_count": 0, "cum_total_count": 472, "cum_lineage_count": 1, "proportion": 0.00211864406779661, "proportion_ci_lower": 0.00022869174251221146, "proportion_ci_upper": 0.00985929983313849}, {"date": "2021-05-27", "name": "Las Vegas", "id": "USA_US-None", "total_count": 2, "lineage_count": 0, "cum_total_count": 42, "cum_lineage_count": 1, "proportion": 0.023809523809523808, "proportion_ci_lower": 0.002581118369002407, "proportion_ci_upper": 0.10592581752281838}, {"date": "2021-05-28", "name": "Louisiana", "id": "USA_US-LA", "total_count": 20, "lineage_count": 0, "cum_total_count": 627, "cum_lineage_count": 0, "proportion": 0.0, "proportion_ci_lower": 7.828367116359557e-07, "proportion_ci_upper": 0.003996683125390859}, {"date": "2021-06-01", "name": "Maine", "id": "USA_US-ME", "total_count": 1, "lineage_count": 0, "cum_total_count": 914, "cum_lineage_count": 1, "proportion": 0.0010940919037199124, "proportion_ci_lower": 0.00011807527024433866, "proportion_ci_upper": 0.005102345034261879}, {"date": "2021-06-03", "name": "Maryland", "id": "USA_US-MD", "total_count": 1, "lineage_count": 0, "cum_total_count": 2798, "cum_lineage_count": 26, "proportion": 0.009292351679771264, "proportion_ci_lower": 0.006223537074556867, "proportion_ci_upper": 0.013373999579257112}, {"date": "2021-05-30", "name": "Massachusetts", "id": "USA_US-MA", "total_count": 8, "lineage_count": 0, "cum_total_count": 7037, "cum_lineage_count": 8, "proportion": 0.001136848088674151, "proportion_ci_lower": 0.0005376002308817948, "proportion_ci_upper": 0.0021440043651580476}, {"date": "2021-05-29", "name": "Michigan", "id": "USA_US-MI", "total_count": 5, "lineage_count": 0, "cum_total_count": 3972, "cum_lineage_count": 18, "proportion": 0.004531722054380665, "proportion_ci_lower": 0.0027849445140435396, "proportion_ci_upper": 0.006998432206069993}, {"date": "2021-06-06", "name": "Minnesota", "id": "USA_US-MN", "total_count": 1, "lineage_count": 0, "cum_total_count": 7751, "cum_lineage_count": 34, "proportion": 0.004386530770223197, "proportion_ci_lower": 0.0030933876416696956, "proportion_ci_upper": 0.006049228078956803}, {"date": "2021-06-01", "name": "Mississippi", "id": "USA_US-MS", "total_count": 2, "lineage_count": 0, "cum_total_count": 228, "cum_lineage_count": 10, "proportion": 0.043859649122807015, "proportion_ci_lower": 0.022769815002352155, "proportion_ci_upper": 0.07640205598473915}, {"date": "2021-05-30", "name": "Missouri", "id": "USA_US-MO", "total_count": 2, "lineage_count": 0, "cum_total_count": 812, "cum_lineage_count": 5, "proportion": 0.006157635467980296, "proportion_ci_lower": 0.002353359517595657, "proportion_ci_upper": 0.013443951550659028}, {"date": "2021-06-02", "name": "Montana", "id": "USA_US-MT", "total_count": 3, "lineage_count": 0, "cum_total_count": 339, "cum_lineage_count": 0, "proportion": 0.0, "proportion_ci_lower": 1.4474106701592774e-06, "proportion_ci_upper": 0.007377050777346677}, {"date": "2021-06-07", "name": "Nebraska", "id": "USA_US-NE", "total_count": 1, "lineage_count": 0, "cum_total_count": 485, "cum_lineage_count": 9, "proportion": 0.018556701030927835, "proportion_ci_lower": 0.009220587190736722, "proportion_ci_upper": 0.033592022093003604}, {"date": "2021-05-30", "name": "Nevada", "id": "USA_US-NV", "total_count": 4, "lineage_count": 0, "cum_total_count": 449, "cum_lineage_count": 1, "proportion": 0.0022271714922048997, "proportion_ci_lower": 0.00024041158769406559, "proportion_ci_upper": 0.010361997058212391}, {"date": "2021-05-30", "name": "New Hampshire", "id": "USA_US-NH", "total_count": 2, "lineage_count": 0, "cum_total_count": 757, "cum_lineage_count": 0, "proportion": 0.0, "proportion_ci_lower": 6.484442028583238e-07, "proportion_ci_upper": 0.0033116949935411773}, {"date": "2021-05-30", "name": "New Jersey", "id": "USA_US-NJ", "total_count": 5, "lineage_count": 0, "cum_total_count": 2719, "cum_lineage_count": 10, "proportion": 0.003677822728944465, "proportion_ci_lower": 0.0018924516814470224, "proportion_ci_upper": 0.006514367571960777}, {"date": "2021-05-30", "name": "New Mexico", "id": "USA_US-NM", "total_count": 1, "lineage_count": 0, "cum_total_count": 890, "cum_lineage_count": 2, "proportion": 0.0022471910112359553, "proportion_ci_lower": 0.0004672576106642835, "proportion_ci_upper": 0.007189388597629742}, {"date": "2021-06-02", "name": "New York", "id": "USA_US-NY", "total_count": 6, "lineage_count": 0, "cum_total_count": 5930, "cum_lineage_count": 37, "proportion": 0.006239460370994941, "proportion_ci_lower": 0.004467690342397247, "proportion_ci_upper": 0.00849248782997436}, {"date": "2021-05-07", "name": "New York, New York County", "id": "USA_US-None", "total_count": 1, "lineage_count": 0, "cum_total_count": 1, "cum_lineage_count": 0, "proportion": 0.0, "proportion_ci_lower": 0.00038558098075590136, "proportion_ci_upper": 0.8532536836904249}, {"date": "2021-06-01", "name": "North Carolina", "id": "USA_US-NC", "total_count": 3, "lineage_count": 0, "cum_total_count": 2857, "cum_lineage_count": 29, "proportion": 0.010150507525376268, "proportion_ci_lower": 0.006951742479797656, "proportion_ci_upper": 0.014339649725300885}, {"date": "2021-05-24", "name": "North Dakota", "id": "USA_US-ND", "total_count": 8, "lineage_count": 0, "cum_total_count": 823, "cum_lineage_count": 0, "proportion": 0.0, "proportion_ci_lower": 5.964584142094917e-07, "proportion_ci_upper": 0.0030466011467760903}, {"date": "2021-04-29", "name": "Northern Mariana Islands", "id": "USA_US-None", "total_count": 1, "lineage_count": 0, "cum_total_count": 1, "cum_lineage_count": 0, "proportion": 0.0, "proportion_ci_lower": 0.00038558098075590136, "proportion_ci_upper": 0.8532536836904249}, {"date": "2021-06-01", "name": "Ohio", "id": "USA_US-OH", "total_count": 4, "lineage_count": 0, "cum_total_count": 2184, "cum_lineage_count": 18, "proportion": 0.008241758241758242, "proportion_ci_lower": 0.005068305826214162, "proportion_ci_upper": 0.012714338876090414}, {"date": "2021-05-29", "name": "Oklahoma", "id": "USA_US-OK", "total_count": 1, "lineage_count": 0, "cum_total_count": 136, "cum_lineage_count": 1, "proportion": 0.007352941176470588, "proportion_ci_lower": 0.0007945126379456283, "proportion_ci_upper": 0.033846645274780096}, {"date": "2021-06-03", "name": "Oregon", "id": "USA_US-OR", "total_count": 1, "lineage_count": 0, "cum_total_count": 1821, "cum_lineage_count": 76, "proportion": 0.04173531026908292, "proportion_ci_lower": 0.0332663670261168, "proportion_ci_upper": 0.051658908794499636}, {"date": "2021-05-28", "name": "Pennsylvania", "id": "USA_US-PA", "total_count": 12, "lineage_count": 1, "cum_total_count": 4101, "cum_lineage_count": 30, "proportion": 0.0073152889539136795, "proportion_ci_lower": 0.0050411868991464045, "proportion_ci_upper": 0.010283485984153184}, {"date": "2021-05-28", "name": "Rhode Island", "id": "USA_US-RI", "total_count": 1, "lineage_count": 0, "cum_total_count": 1248, "cum_lineage_count": 5, "proportion": 0.004006410256410256, "proportion_ci_lower": 0.0015303358186253503, "proportion_ci_upper": 0.008759362512194557}, {"date": "2021-05-30", "name": "South Carolina", "id": "USA_US-SC", "total_count": 1, "lineage_count": 0, "cum_total_count": 534, "cum_lineage_count": 13, "proportion": 0.024344569288389514, "proportion_ci_lower": 0.01371276344326478, "proportion_ci_upper": 0.040099870995380815}, {"date": "2021-05-23", "name": "South Dakota", "id": "USA_US-SD", "total_count": 1, "lineage_count": 0, "cum_total_count": 113, "cum_lineage_count": 0, "proportion": 0.0, "proportion_ci_lower": 4.335826024442665e-06, "proportion_ci_upper": 0.021936192687970407}, {"date": "2021-06-01", "name": "Tennessee", "id": "USA_US-TN", "total_count": 6, "lineage_count": 0, "cum_total_count": 1151, "cum_lineage_count": 7, "proportion": 0.006081668114682885, "proportion_ci_lower": 0.00272429488818271, "proportion_ci_upper": 0.01190354460670684}, {"date": "2021-06-01", "name": "Texas", "id": "USA_US-TX", "total_count": 3, "lineage_count": 0, "cum_total_count": 5964, "cum_lineage_count": 12, "proportion": 0.002012072434607646, "proportion_ci_lower": 0.0011003653763999115, "proportion_ci_upper": 0.0034051311228048275}, {"date": "2021-05-20", "name": "Unknown", "id": "USA_US-None", "total_count": 2, "lineage_count": 0, "cum_total_count": 18, "cum_lineage_count": 0, "proportion": 0.0, "proportion_ci_lower": 2.690311730090928e-05, "proportion_ci_upper": 0.12855821182175955}, {"date": "2021-05-31", "name": "Utah", "id": "USA_US-UT", "total_count": 1, "lineage_count": 0, "cum_total_count": 1249, "cum_lineage_count": 17, "proportion": 0.013610888710968775, "proportion_ci_lower": 0.008254935815682086, "proportion_ci_upper": 0.021212215173814997}, {"date": "2021-05-28", "name": "Vermont", "id": "USA_US-VT", "total_count": 1, "lineage_count": 0, "cum_total_count": 514, "cum_lineage_count": 2, "proportion": 0.0038910505836575876, "proportion_ci_lower": 0.000809426144933316, "proportion_ci_upper": 0.01242343307357252}, {"date": "2021-05-30", "name": "Virgin Islands", "id": "USA_US-None", "total_count": 1, "lineage_count": 0, "cum_total_count": 1, "cum_lineage_count": 0, "proportion": 0.0, "proportion_ci_lower": 0.00038558098075590136, "proportion_ci_upper": 0.8532536836904249}, {"date": "2021-05-09", "name": "Virgin Islands of the U.S.", "id": "USA_US-None", "total_count": 1, "lineage_count": 0, "cum_total_count": 10, "cum_lineage_count": 0, "proportion": 0.0, "proportion_ci_lower": 4.789043315758197e-05, "proportion_ci_upper": 0.21719626750921056}, {"date": "2021-06-01", "name": "Virginia", "id": "USA_US-VA", "total_count": 5, "lineage_count": 0, "cum_total_count": 1546, "cum_lineage_count": 20, "proportion": 0.0129366106080207, "proportion_ci_lower": 0.008173029477261841, "proportion_ci_upper": 0.019517881920059987}, {"date": "2021-06-03", "name": "Washington", "id": "USA_US-WA", "total_count": 5, "lineage_count": 0, "cum_total_count": 7931, "cum_lineage_count": 147, "proportion": 0.018534863195057368, "proportion_ci_lower": 0.015739477195618357, "proportion_ci_upper": 0.02168147917605101}, {"date": "2021-05-29", "name": "West Virginia", "id": "USA_US-WV", "total_count": 1, "lineage_count": 0, "cum_total_count": 1538, "cum_lineage_count": 4, "proportion": 0.002600780234070221, "proportion_ci_lower": 0.000878504252869297, "proportion_ci_upper": 0.006172178633425673}, {"date": "2021-06-07", "name": "Wisconsin", "id": "USA_US-WI", "total_count": 1, "lineage_count": 0, "cum_total_count": 1998, "cum_lineage_count": 13, "proportion": 0.0065065065065065065, "proportion_ci_lower": 0.003651763234238549, "proportion_ci_upper": 0.010784830147174906}, {"date": "2021-06-01", "name": "Wyoming", "id": "USA_US-WY", "total_count": 7, "lineage_count": 0, "cum_total_count": 532, "cum_lineage_count": 0, "proportion": 0.0, "proportion_ci_lower": 9.225632276156556e-07, "proportion_ci_upper": 0.004708359112657517}]}