{"success": true, "results": [{"date": "2021-06-03", "name": "Alabama", "id": "USA_US-AL", "total_count": 3, "lineage_count": 0, "cum_total_count": 223, "cum_lineage_count": 0, "proportion": 0.0, "proportion_ci_lower": 2.199479106829827e-06, "proportion_ci_upper": 0.011188622445017147}, {"date": "2021-06-04", "name": "Alaska", "id": "USA_US-AK", "total_count": 7, "lineage_count": 0, "cum_total_count": 891, "cum_lineage_count": 4, "proportion": 0.004489337822671156, "proportion_ci_lower": 0.0015172020647661276, "proportion_ci_upper": 0.010638992548903548}, {"date": "2021-06-04", "name": "Arizona", "id": "USA_US-AZ", "total_count": 2, "lineage_count": 0, "cum_total_count": 1766, "cum_lineage_count": 11, "proportion": 0.00622876557191393, "proportion_ci_lower": 0.003313703030623962, "proportion_ci_upper": 0.010754136477449494}, {"date": "2021-06-04", "name": "Arkansas", "id": "USA_US-AR", "total_count": 2, "lineage_count": 0, "cum_total_count": 267, "cum_lineage_count": 1, "proportion": 0.003745318352059925, "proportion_ci_lower": 0.00040440826564692235, "proportion_ci_upper": 0.017370185939152294}, {"date": "2021-06-06", "name": "California", "id": "USA_US-CA", "total_count": 10, "lineage_count": 0, "cum_total_count": 6769, "cum_lineage_count": 33, "proportion": 0.004875166198847688, "proportion_ci_lower": 0.0034194937979076124, "proportion_ci_upper": 0.006753558668328163}, {"date": "2021-05-17", "name": "California, Los Angeles County", "id": "USA_US-None", "total_count": 1, "lineage_count": 0, "cum_total_count": 3, "cum_lineage_count": 0, "proportion": 0.0, "proportion_ci_lower": 0.00015063602543656854, "proportion_ci_upper": 0.5355832430429506}, {"date": "2021-06-04", "name": "Colorado", "id": "USA_US-CO", "total_count": 6, "lineage_count": 0, "cum_total_count": 5460, "cum_lineage_count": 9, "proportion": 0.0016483516483516484, "proportion_ci_lower": 0.0008159175255729988, "proportion_ci_upper": 0.003006271464533805}, {"date": "2021-06-01", "name": "Connecticut", "id": "USA_US-CT", "total_count": 8, "lineage_count": 0, "cum_total_count": 1874, "cum_lineage_count": 12, "proportion": 0.0064034151547491995, "proportion_ci_lower": 0.0035050849109956785, "proportion_ci_upper": 0.010819316118724998}, {"date": "2021-05-26", "name": "Delaware", "id": "USA_US-DE", "total_count": 1, "lineage_count": 0, "cum_total_count": 534, "cum_lineage_count": 0, "proportion": 0.0, "proportion_ci_lower": 9.191095538626795e-07, "proportion_ci_upper": 0.004690774475909798}, {"date": "2021-06-03", "name": "District of Columbia", "id": "USA_US-DC", "total_count": 1, "lineage_count": 0, "cum_total_count": 200, "cum_lineage_count": 0, "proportion": 0.0, "proportion_ci_lower": 2.4521027404097352e-06, "proportion_ci_upper": 0.012465661135917114}, {"date": "2021-06-04", "name": "Florida", "id": "USA_US-FL", "total_count": 14, "lineage_count": 0, "cum_total_count": 7927, "cum_lineage_count": 28, "proportion": 0.0035322316134729407, "proportion_ci_lower": 0.0023998437608901595, "proportion_ci_upper": 0.00502648647975279}, {"date": "2021-06-09", "name": "Georgia", "id": "USA_US-GA", "total_count": 8, "lineage_count": 0, "cum_total_count": 1351, "cum_lineage_count": 24, "proportion": 0.01776461880088823, "proportion_ci_lower": 0.011711956565167846, "proportion_ci_upper": 0.025877228391594675}, {"date": "2021-05-11", "name": "Guam", "id": "USA_US-None", "total_count": 3, "lineage_count": 0, "cum_total_count": 18, "cum_lineage_count": 1, "proportion": 0.05555555555555555, "proportion_ci_lower": 0.006061344165326898, "proportion_ci_upper": 0.231611808489526}, {"date": "2021-05-28", "name": "Hawaii", "id": "USA_US-HI", "total_count": 1, "lineage_count": 0, "cum_total_count": 198, "cum_lineage_count": 1, "proportion": 0.005050505050505051, "proportion_ci_lower": 0.0005454784353271957, "proportion_ci_upper": 0.02335984860781737}, {"date": "2021-06-01", "name": "Idaho", "id": "USA_US-ID", "total_count": 2, "lineage_count": 0, "cum_total_count": 192, "cum_lineage_count": 0, "proportion": 0.0, "proportion_ci_lower": 2.5541405263722507e-06, "proportion_ci_upper": 0.012981004802901652}, {"date": "2021-06-03", "name": "Illinois", "id": "USA_US-IL", "total_count": 7, "lineage_count": 0, "cum_total_count": 5478, "cum_lineage_count": 50, "proportion": 0.009127418765972983, "proportion_ci_lower": 0.006860686311050395, "proportion_ci_upper": 0.011912230704880677}, {"date": "2021-06-04", "name": "Indiana", "id": "USA_US-IN", "total_count": 29, "lineage_count": 1, "cum_total_count": 2461, "cum_lineage_count": 13, "proportion": 0.005282405526208858, "proportion_ci_lower": 0.0029640088869201625, "proportion_ci_upper": 0.008759585442212448}, {"date": "2021-06-03", "name": "Iowa", "id": "USA_US-IA", "total_count": 1, "lineage_count": 0, "cum_total_count": 176, "cum_lineage_count": 0, "proportion": 0.0, "proportion_ci_lower": 2.7860049954209005e-06, "proportion_ci_upper": 0.014151040347032323}, {"date": "2021-06-10", "name": "Kansas", "id": "USA_US-KS", "total_count": 1, "lineage_count": 0, "cum_total_count": 1263, "cum_lineage_count": 4, "proportion": 0.003167062549485352, "proportion_ci_lower": 0.0010699489782613144, "proportion_ci_upper": 0.007512882519569719}, {"date": "2021-06-04", "name": "Kentucky", "id": "USA_US-KY", "total_count": 2, "lineage_count": 0, "cum_total_count": 561, "cum_lineage_count": 1, "proportion": 0.0017825311942959, "proportion_ci_lower": 0.00019239818094629653, "proportion_ci_upper": 0.008300984084252727}, {"date": "2021-05-27", "name": "Las Vegas", "id": "USA_US-None", "total_count": 2, "lineage_count": 0, "cum_total_count": 42, "cum_lineage_count": 1, "proportion": 0.023809523809523808, "proportion_ci_lower": 0.002581118369002407, "proportion_ci_upper": 0.10592581752281838}, {"date": "2021-06-03", "name": "Louisiana", "id": "USA_US-LA", "total_count": 2, "lineage_count": 0, "cum_total_count": 621, "cum_lineage_count": 0, "proportion": 0.0, "proportion_ci_lower": 7.903973034369228e-07, "proportion_ci_upper": 0.004035204881903683}, {"date": "2021-06-01", "name": "Maine", "id": "USA_US-ME", "total_count": 4, "lineage_count": 0, "cum_total_count": 866, "cum_lineage_count": 0, "proportion": 0.0, "proportion_ci_lower": 5.668506770098685e-07, "proportion_ci_upper": 0.0028955893550138864}, {"date": "2021-06-03", "name": "Maryland", "id": "USA_US-MD", "total_count": 4, "lineage_count": 0, "cum_total_count": 2564, "cum_lineage_count": 23, "proportion": 0.008970358814352574, "proportion_ci_lower": 0.0058502895743488825, "proportion_ci_upper": 0.013196109697606206}, {"date": "2021-06-04", "name": "Massachusetts", "id": "USA_US-MA", "total_count": 2, "lineage_count": 0, "cum_total_count": 6399, "cum_lineage_count": 6, "proportion": 0.0009376465072667605, "proportion_ci_lower": 0.0003914614314756997, "proportion_ci_upper": 0.00193173411215819}, {"date": "2021-06-03", "name": "Michigan", "id": "USA_US-MI", "total_count": 2, "lineage_count": 0, "cum_total_count": 3372, "cum_lineage_count": 16, "proportion": 0.004744958481613286, "proportion_ci_lower": 0.0028267456486849914, "proportion_ci_upper": 0.007510511803107356}, {"date": "2021-06-06", "name": "Minnesota", "id": "USA_US-MN", "total_count": 2, "lineage_count": 0, "cum_total_count": 7332, "cum_lineage_count": 31, "proportion": 0.004228041462084015, "proportion_ci_lower": 0.0029307657389753294, "proportion_ci_upper": 0.005916058912103117}, {"date": "2021-06-04", "name": "Mississippi", "id": "USA_US-MS", "total_count": 1, "lineage_count": 0, "cum_total_count": 224, "cum_lineage_count": 10, "proportion": 0.044642857142857144, "proportion_ci_lower": 0.023180487336462406, "proportion_ci_upper": 0.07774094615991045}, {"date": "2021-06-04", "name": "Missouri", "id": "USA_US-MO", "total_count": 1, "lineage_count": 0, "cum_total_count": 810, "cum_lineage_count": 5, "proportion": 0.006172839506172839, "proportion_ci_lower": 0.002359179617083331, "proportion_ci_upper": 0.013477013968473561}, {"date": "2021-06-08", "name": "Montana", "id": "USA_US-MT", "total_count": 8, "lineage_count": 0, "cum_total_count": 376, "cum_lineage_count": 0, "proportion": 0.0, "proportion_ci_lower": 1.3050740989750197e-06, "proportion_ci_upper": 0.0066540200834785445}, {"date": "2021-06-10", "name": "Nebraska", "id": "USA_US-NE", "total_count": 1, "lineage_count": 0, "cum_total_count": 443, "cum_lineage_count": 9, "proportion": 0.020316027088036117, "proportion_ci_lower": 0.010098816600011691, "proportion_ci_upper": 0.03674817798572638}, {"date": "2021-06-02", "name": "Nevada", "id": "USA_US-NV", "total_count": 3, "lineage_count": 0, "cum_total_count": 406, "cum_lineage_count": 1, "proportion": 0.0024630541871921183, "proportion_ci_lower": 0.000265886215727543, "proportion_ci_upper": 0.011453816147580231}, {"date": "2021-06-01", "name": "New Hampshire", "id": "USA_US-NH", "total_count": 2, "lineage_count": 0, "cum_total_count": 707, "cum_lineage_count": 0, "proportion": 0.0, "proportion_ci_lower": 6.94286825650678e-07, "proportion_ci_upper": 0.003545404188009997}, {"date": "2021-06-04", "name": "New Jersey", "id": "USA_US-NJ", "total_count": 3, "lineage_count": 0, "cum_total_count": 2356, "cum_lineage_count": 10, "proportion": 0.004244482173174873, "proportion_ci_lower": 0.002184301000889831, "proportion_ci_upper": 0.007516309862594106}, {"date": "2021-06-03", "name": "New Mexico", "id": "USA_US-NM", "total_count": 1, "lineage_count": 0, "cum_total_count": 839, "cum_lineage_count": 2, "proportion": 0.0023837902264600714, "proportion_ci_lower": 0.0004956790210613464, "proportion_ci_upper": 0.007625127422343891}, {"date": "2021-06-03", "name": "New York", "id": "USA_US-NY", "total_count": 4, "lineage_count": 0, "cum_total_count": 5208, "cum_lineage_count": 35, "proportion": 0.006720430107526882, "proportion_ci_lower": 0.004765598114102138, "proportion_ci_upper": 0.009222645437302557}, {"date": "2021-05-07", "name": "New York, New York County", "id": "USA_US-None", "total_count": 1, "lineage_count": 0, "cum_total_count": 1, "cum_lineage_count": 0, "proportion": 0.0, "proportion_ci_lower": 0.00038558098075590136, "proportion_ci_upper": 0.8532536836904249}, {"date": "2021-06-04", "name": "North Carolina", "id": "USA_US-NC", "total_count": 3, "lineage_count": 0, "cum_total_count": 2657, "cum_lineage_count": 24, "proportion": 0.009032743695897629, "proportion_ci_lower": 0.00594673104952684, "proportion_ci_upper": 0.013185713023615708}, {"date": "2021-05-24", "name": "North Dakota", "id": "USA_US-ND", "total_count": 8, "lineage_count": 0, "cum_total_count": 776, "cum_lineage_count": 0, "proportion": 0.0, "proportion_ci_lower": 6.325724673832383e-07, "proportion_ci_upper": 0.0032307668998493664}, {"date": "2021-04-29", "name": "Northern Mariana Islands", "id": "USA_US-None", "total_count": 1, "lineage_count": 0, "cum_total_count": 1, "cum_lineage_count": 0, "proportion": 0.0, "proportion_ci_lower": 0.00038558098075590136, "proportion_ci_upper": 0.8532536836904249}, {"date": "2021-06-08", "name": "Ohio", "id": "USA_US-OH", "total_count": 1, "lineage_count": 0, "cum_total_count": 2170, "cum_lineage_count": 17, "proportion": 0.00783410138248848, "proportion_ci_lower": 0.004746295975191262, "proportion_ci_upper": 0.012230296235410054}, {"date": "2021-06-03", "name": "Oklahoma", "id": "USA_US-OK", "total_count": 1, "lineage_count": 0, "cum_total_count": 133, "cum_lineage_count": 1, "proportion": 0.007518796992481203, "proportion_ci_lower": 0.0008124605393992122, "proportion_ci_upper": 0.03459816823952011}, {"date": "2021-06-04", "name": "Oregon", "id": "USA_US-OR", "total_count": 3, "lineage_count": 0, "cum_total_count": 1763, "cum_lineage_count": 66, "proportion": 0.03743618831537152, "proportion_ci_lower": 0.02932011202983493, "proportion_ci_upper": 0.047068689205563286}, {"date": "2021-06-04", "name": "Pennsylvania", "id": "USA_US-PA", "total_count": 3, "lineage_count": 0, "cum_total_count": 3665, "cum_lineage_count": 23, "proportion": 0.006275579809004093, "proportion_ci_lower": 0.004090997104569134, "proportion_ci_upper": 0.009238066847324089}, {"date": "2021-06-02", "name": "Rhode Island", "id": "USA_US-RI", "total_count": 1, "lineage_count": 0, "cum_total_count": 1140, "cum_lineage_count": 5, "proportion": 0.0043859649122807015, "proportion_ci_lower": 0.0016754802884992853, "proportion_ci_upper": 0.009586844073660283}, {"date": "2021-05-30", "name": "South Carolina", "id": "USA_US-SC", "total_count": 1, "lineage_count": 0, "cum_total_count": 626, "cum_lineage_count": 15, "proportion": 0.023961661341853034, "proportion_ci_lower": 0.014073315122501262, "proportion_ci_upper": 0.038227903875276525}, {"date": "2021-05-23", "name": "South Dakota", "id": "USA_US-SD", "total_count": 1, "lineage_count": 0, "cum_total_count": 107, "cum_lineage_count": 0, "proportion": 0.0, "proportion_ci_lower": 4.578387879384091e-06, "proportion_ci_upper": 0.023149062905532237}, {"date": "2021-06-03", "name": "Tennessee", "id": "USA_US-TN", "total_count": 17, "lineage_count": 0, "cum_total_count": 1137, "cum_lineage_count": 7, "proportion": 0.006156552330694811, "proportion_ci_lower": 0.0027578893073506457, "proportion_ci_upper": 0.012049646569841754}, {"date": "2021-06-04", "name": "Texas", "id": "USA_US-TX", "total_count": 8, "lineage_count": 0, "cum_total_count": 5585, "cum_lineage_count": 12, "proportion": 0.0021486123545210387, "proportion_ci_lower": 0.001175069612503507, "proportion_ci_upper": 0.0036360218360222962}, {"date": "2021-05-22", "name": "Unknown", "id": "USA_US-None", "total_count": 1, "lineage_count": 0, "cum_total_count": 16, "cum_lineage_count": 0, "proportion": 0.0, "proportion_ci_lower": 3.0213479978023642e-05, "proportion_ci_upper": 0.1431841379314448}, {"date": "2021-06-04", "name": "Utah", "id": "USA_US-UT", "total_count": 6, "lineage_count": 0, "cum_total_count": 1197, "cum_lineage_count": 17, "proportion": 0.014202172096908938, "proportion_ci_lower": 0.008614485132004192, "proportion_ci_upper": 0.02212980755572369}, {"date": "2021-05-31", "name": "Vermont", "id": "USA_US-VT", "total_count": 1, "lineage_count": 0, "cum_total_count": 470, "cum_lineage_count": 2, "proportion": 0.00425531914893617, "proportion_ci_lower": 0.0008852898784889557, "proportion_ci_upper": 0.013580398559805307}, {"date": "2021-05-30", "name": "Virgin Islands", "id": "USA_US-None", "total_count": 1, "lineage_count": 0, "cum_total_count": 1, "cum_lineage_count": 0, "proportion": 0.0, "proportion_ci_lower": 0.00038558098075590136, "proportion_ci_upper": 0.8532536836904249}, {"date": "2021-05-09", "name": "Virgin Islands of the U.S.", "id": "USA_US-None", "total_count": 1, "lineage_count": 0, "cum_total_count": 10, "cum_lineage_count": 0, "proportion": 0.0, "proportion_ci_lower": 4.789043315758197e-05, "proportion_ci_upper": 0.21719626750921056}, {"date": "2021-06-03", "name": "Virginia", "id": "USA_US-VA", "total_count": 1, "lineage_count": 0, "cum_total_count": 1419, "cum_lineage_count": 17, "proportion": 0.011980267794221282, "proportion_ci_lower": 0.007263790122780183, "proportion_ci_upper": 0.0186800241295777}, {"date": "2021-06-04", "name": "Washington", "id": "USA_US-WA", "total_count": 1, "lineage_count": 0, "cum_total_count": 7834, "cum_lineage_count": 146, "proportion": 0.018636711769211133, "proportion_ci_lower": 0.015817063929818218, "proportion_ci_upper": 0.02181186167701743}, {"date": "2021-06-04", "name": "West Virginia", "id": "USA_US-WV", "total_count": 1, "lineage_count": 0, "cum_total_count": 1437, "cum_lineage_count": 4, "proportion": 0.0027835768963117608, "proportion_ci_lower": 0.0009402964732708013, "proportion_ci_upper": 0.006605084502713687}, {"date": "2021-06-07", "name": "Wisconsin", "id": "USA_US-WI", "total_count": 1, "lineage_count": 0, "cum_total_count": 1864, "cum_lineage_count": 13, "proportion": 0.006974248927038627, "proportion_ci_lower": 0.003914651338802976, "proportion_ci_upper": 0.011558238462317294}, {"date": "2021-06-04", "name": "Wyoming", "id": "USA_US-WY", "total_count": 1, "lineage_count": 0, "cum_total_count": 519, "cum_lineage_count": 0, "proportion": 0.0, "proportion_ci_lower": 9.456606056427626e-07, "proportion_ci_upper": 0.004825953143915131}]}